peanutdb/__init__.py
peanutdb/peanutdb.py
peanutdb-0.2.0.dist-info/DESCRIPTION.rst
peanutdb-0.2.0.dist-info/METADATA
peanutdb-0.2.0.dist-info/RECORD
peanutdb-0.2.0.dist-info/WHEEL
peanutdb-0.2.0.dist-info/metadata.json
peanutdb-0.2.0.dist-info/top_level.txt
