Metadata-Version: 2.0
Name: peanutdb
Version: 0.2.0
Summary: A JSON based database for quick prototyping and playing.
Home-page: https://github.com/ahmednooor/peanutdb
Author: Ahmed Noor
Author-email: m.ahmednoor7@yahoo.com
License: MIT
Download-URL: https://github.com/ahmednooor/peanutdb/tarball/0.2.0
